.gitignore
.travis.yml
LICENSE
README.rst
post-receive.example
requirements.txt
setup.cfg
setup.py
tox.ini
blogtopoid/__init__.py
blogtopoid/blogtopoid.py
blogtopoid/commands.py
blogtopoid/decorators.py
blogtopoid.egg-info/PKG-INFO
blogtopoid.egg-info/SOURCES.txt
blogtopoid.egg-info/dependency_links.txt
blogtopoid.egg-info/entry_points.txt
blogtopoid.egg-info/requires.txt
blogtopoid.egg-info/top_level.txt
blogtopoid.egg-info/zip-safe
blogtopoid/example/19700101 example.md
blogtopoid/example/19700101 pythonlogo.png
blogtopoid/example/blogtopoid.config.example
blogtopoid/example/index.html
blogtopoid/example/page.html
blogtopoid/example/post.html
blogtopoid/test/__init__.py
blogtopoid/test/test_blogtopoid.py
blogtopoid/test/test_decorators.py
doc/Makefile
doc/make.bat
doc/source/api.rst
doc/source/conf.py
doc/source/index.rst
doc/source/manual.rst
doc/source/templates.rst