Metadata-Version: 1.1
Name: blogtopoid
Version: 0.0.1b
Summary: simple blog generator
Home-page: https://github.com/hansenerd/blogtopoid/
Author: chris
Author-email: cg@zknt.org
License: MIT
Platform: UNKNOWN
Classifier: Development Status :: 2 - Pre-Alpha
Classifier: Environment :: Console
Classifier: Intended Audience :: End Users/Desktop
Classifier: License :: OSI Approved :: MIT License
Classifier: Operating System :: OS Independent
Classifier: Programming Language :: Python
Classifier: Topic :: Internet :: WWW/HTTP :: Dynamic Content :: News/Diary
